[
  {
    "id": "2415",
    "Type": "string",
    "Attribute": "ADSL-Agent-Circuit-Id",
    "Value": null,
    "Format": null,
    "Vendor": "ADSL-Forum",
    "RecommendedOP": null,
    "RecommendedTable": null,
    "RecommendedHelper": null,
    "RecommendedTooltip": null
  },
  {
    "id": "2416",
    "Type": "string",
    "Attribute": "ADSL-Agent-Remote-Id",
    "Value": null,
    "Format": null,
    "Vendor": "ADSL-Forum",
    "RecommendedOP": null,
    "RecommendedTable": null,
    "RecommendedHelper": null,
    "RecommendedTooltip": null
  },
  {
    "id": "2417",
    "Type": "integer",
    "Attribute": "Actual-Data-Rate-Upstream",
    "Value": null,
    "Format": null,
    "Vendor": "ADSL-Forum",
    "RecommendedOP": null,
    "RecommendedTable": null,
    "RecommendedHelper": null,
    "RecommendedTooltip": null
  },
  {
    "id": "2418",
    "Type": "integer",
    "Attribute": "Actual-Data-Rate-Downstream",
    "Value": null,
    "Format": null,
    "Vendor": "ADSL-Forum",
    "RecommendedOP": null,
    "RecommendedTable": null,
    "RecommendedHelper": null,
    "RecommendedTooltip": null
  },
  {
    "id": "2419",
    "Type": "integer",
    "Attribute": "Minimum-Data-Rate-Upstream",
    "Value": null,
    "Format": null,
    "Vendor": "ADSL-Forum",
    "RecommendedOP": null,
    "RecommendedTable": null,
    "RecommendedHelper": null,
    "RecommendedTooltip": null
  },
  {
    "id": "2420",
    "Type": "integer",
    "Attribute": "Minimum-Data-Rate-Downstream",
    "Value": null,
    "Format": null,
    "Vendor": "ADSL-Forum",
    "RecommendedOP": null,
    "RecommendedTable": null,
    "RecommendedHelper": null,
    "RecommendedTooltip": null
  },
  {
    "id": "2421",
    "Type": "integer",
    "Attribute": "Attainable-Data-Rate-Upstream",
    "Value": null,
    "Format": null,
    "Vendor": "ADSL-Forum",
    "RecommendedOP": null,
    "RecommendedTable": null,
    "RecommendedHelper": null,
    "RecommendedTooltip": null
  },
  {
    "id": "2422",
    "Type": "integer",
    "Attribute": "Attainable-Data-Rate-Downstream",
    "Value": null,
    "Format": null,
    "Vendor": "ADSL-Forum",
    "RecommendedOP": null,
    "RecommendedTable": null,
    "RecommendedHelper": null,
    "RecommendedTooltip": null
  },
  {
    "id": "2423",
    "Type": "integer",
    "Attribute": "Maximum-Data-Rate-Upstream",
    "Value": null,
    "Format": null,
    "Vendor": "ADSL-Forum",
    "RecommendedOP": null,
    "RecommendedTable": null,
    "RecommendedHelper": null,
    "RecommendedTooltip": null
  },
  {
    "id": "2424",
    "Type": "integer",
    "Attribute": "Maximum-Data-Rate-Downstream",
    "Value": null,
    "Format": null,
    "Vendor": "ADSL-Forum",
    "RecommendedOP": null,
    "RecommendedTable": null,
    "RecommendedHelper": null,
    "RecommendedTooltip": null
  },
  {
    "id": "2425",
    "Type": "integer",
    "Attribute": "Minimum-Data-Rate-Upstream-Low-Power",
    "Value": null,
    "Format": null,
    "Vendor": "ADSL-Forum",
    "RecommendedOP": null,
    "RecommendedTable": null,
    "RecommendedHelper": null,
    "RecommendedTooltip": null
  },
  {
    "id": "2426",
    "Type": "integer",
    "Attribute": "Minimum-Data-Rate-Downstream-Low-Power",
    "Value": null,
    "Format": null,
    "Vendor": "ADSL-Forum",
    "RecommendedOP": null,
    "RecommendedTable": null,
    "RecommendedHelper": null,
    "RecommendedTooltip": null
  },
  {
    "id": "2427",
    "Type": "integer",
    "Attribute": "Maximum-Interleaving-Delay-Upstream",
    "Value": null,
    "Format": null,
    "Vendor": "ADSL-Forum",
    "RecommendedOP": null,
    "RecommendedTable": null,
    "RecommendedHelper": null,
    "RecommendedTooltip": null
  },
  {
    "id": "2428",
    "Type": "integer",
    "Attribute": "Actual-Interleaving-Delay-Upstream",
    "Value": null,
    "Format": null,
    "Vendor": "ADSL-Forum",
    "RecommendedOP": null,
    "RecommendedTable": null,
    "RecommendedHelper": null,
    "RecommendedTooltip": null
  },
  {
    "id": "2429",
    "Type": "integer",
    "Attribute": "Maximum-Interleaving-Delay-Downstream",
    "Value": null,
    "Format": null,
    "Vendor": "ADSL-Forum",
    "RecommendedOP": null,
    "RecommendedTable": null,
    "RecommendedHelper": null,
    "RecommendedTooltip": null
  },
  {
    "id": "2430",
    "Type": "integer",
    "Attribute": "Actual-Interleaving-Delay-Downstream",
    "Value": null,
    "Format": null,
    "Vendor": "ADSL-Forum",
    "RecommendedOP": null,
    "RecommendedTable": null,
    "RecommendedHelper": null,
    "RecommendedTooltip": null
  },
  {
    "id": "2431",
    "Type": "octets",
    "Attribute": "Access-Loop-Encapsulation",
    "Value": null,
    "Format": null,
    "Vendor": "ADSL-Forum",
    "RecommendedOP": null,
    "RecommendedTable": null,
    "RecommendedHelper": null,
    "RecommendedTooltip": null
  },
  {
    "id": "2432",
    "Type": "octets",
    "Attribute": "IWF-Session",
    "Value": null,
    "Format": null,
    "Vendor": "ADSL-Forum",
    "RecommendedOP": null,
    "RecommendedTable": null,
    "RecommendedHelper": null,
    "RecommendedTooltip": null
  }
]