[
  {
    "id": "3335",
    "Type": "integer",
    "Attribute": "Error-Cause",
    "Value": null,
    "Format": null,
    "Vendor": "dictionary.rfc3576",
    "RecommendedOP": null,
    "RecommendedTable": null,
    "RecommendedHelper": null,
    "RecommendedTooltip": null
  },
  {
    "id": "3336",
    "Type": null,
    "Attribute": "Service-Type",
    "Value": "Authorize-Only",
    "Format": null,
    "Vendor": "dictionary.rfc3576",
    "RecommendedOP": null,
    "RecommendedTable": null,
    "RecommendedHelper": null,
    "RecommendedTooltip": null
  },
  {
    "id": "3337",
    "Type": null,
    "Attribute": "Error-Cause",
    "Value": "Residual-Context-Removed",
    "Format": null,
    "Vendor": "dictionary.rfc3576",
    "RecommendedOP": null,
    "RecommendedTable": null,
    "RecommendedHelper": null,
    "RecommendedTooltip": null
  },
  {
    "id": "3338",
    "Type": null,
    "Attribute": "Error-Cause",
    "Value": "Invalid-EAP-Packet",
    "Format": null,
    "Vendor": "dictionary.rfc3576",
    "RecommendedOP": null,
    "RecommendedTable": null,
    "RecommendedHelper": null,
    "RecommendedTooltip": null
  },
  {
    "id": "3339",
    "Type": null,
    "Attribute": "Error-Cause",
    "Value": "Unsupported-Attribute",
    "Format": null,
    "Vendor": "dictionary.rfc3576",
    "RecommendedOP": null,
    "RecommendedTable": null,
    "RecommendedHelper": null,
    "RecommendedTooltip": null
  },
  {
    "id": "3340",
    "Type": null,
    "Attribute": "Error-Cause",
    "Value": "Missing-Attribute",
    "Format": null,
    "Vendor": "dictionary.rfc3576",
    "RecommendedOP": null,
    "RecommendedTable": null,
    "RecommendedHelper": null,
    "RecommendedTooltip": null
  },
  {
    "id": "3341",
    "Type": null,
    "Attribute": "Error-Cause",
    "Value": "NAS-Identification-Mismatch",
    "Format": null,
    "Vendor": "dictionary.rfc3576",
    "RecommendedOP": null,
    "RecommendedTable": null,
    "RecommendedHelper": null,
    "RecommendedTooltip": null
  },
  {
    "id": "3342",
    "Type": null,
    "Attribute": "Error-Cause",
    "Value": "Invalid-Request",
    "Format": null,
    "Vendor": "dictionary.rfc3576",
    "RecommendedOP": null,
    "RecommendedTable": null,
    "RecommendedHelper": null,
    "RecommendedTooltip": null
  },
  {
    "id": "3343",
    "Type": null,
    "Attribute": "Error-Cause",
    "Value": "Unsupported-Service",
    "Format": null,
    "Vendor": "dictionary.rfc3576",
    "RecommendedOP": null,
    "RecommendedTable": null,
    "RecommendedHelper": null,
    "RecommendedTooltip": null
  },
  {
    "id": "3344",
    "Type": null,
    "Attribute": "Error-Cause",
    "Value": "Unsupported-Extension",
    "Format": null,
    "Vendor": "dictionary.rfc3576",
    "RecommendedOP": null,
    "RecommendedTable": null,
    "RecommendedHelper": null,
    "RecommendedTooltip": null
  },
  {
    "id": "3345",
    "Type": null,
    "Attribute": "Error-Cause",
    "Value": "Administratively-Prohibited",
    "Format": null,
    "Vendor": "dictionary.rfc3576",
    "RecommendedOP": null,
    "RecommendedTable": null,
    "RecommendedHelper": null,
    "RecommendedTooltip": null
  },
  {
    "id": "3346",
    "Type": null,
    "Attribute": "Error-Cause",
    "Value": "Proxy-Request-Not-Routable",
    "Format": null,
    "Vendor": "dictionary.rfc3576",
    "RecommendedOP": null,
    "RecommendedTable": null,
    "RecommendedHelper": null,
    "RecommendedTooltip": null
  },
  {
    "id": "3347",
    "Type": null,
    "Attribute": "Error-Cause",
    "Value": "Session-Context-Not-Found",
    "Format": null,
    "Vendor": "dictionary.rfc3576",
    "RecommendedOP": null,
    "RecommendedTable": null,
    "RecommendedHelper": null,
    "RecommendedTooltip": null
  },
  {
    "id": "3348",
    "Type": null,
    "Attribute": "Error-Cause",
    "Value": "Session-Context-Not-Removable",
    "Format": null,
    "Vendor": "dictionary.rfc3576",
    "RecommendedOP": null,
    "RecommendedTable": null,
    "RecommendedHelper": null,
    "RecommendedTooltip": null
  },
  {
    "id": "3349",
    "Type": null,
    "Attribute": "Error-Cause",
    "Value": "Proxy-Processing-Error",
    "Format": null,
    "Vendor": "dictionary.rfc3576",
    "RecommendedOP": null,
    "RecommendedTable": null,
    "RecommendedHelper": null,
    "RecommendedTooltip": null
  },
  {
    "id": "3350",
    "Type": null,
    "Attribute": "Error-Cause",
    "Value": "Resources-Unavailable",
    "Format": null,
    "Vendor": "dictionary.rfc3576",
    "RecommendedOP": null,
    "RecommendedTable": null,
    "RecommendedHelper": null,
    "RecommendedTooltip": null
  },
  {
    "id": "3351",
    "Type": null,
    "Attribute": "Error-Cause",
    "Value": "Request-Initiated",
    "Format": null,
    "Vendor": "dictionary.rfc3576",
    "RecommendedOP": null,
    "RecommendedTable": null,
    "RecommendedHelper": null,
    "RecommendedTooltip": null
  }
]